{
  "İLÇE": [
    "Arnavutköy",
    "Avcılar",
    "Bahçelievler",
    "Bakırköy",
    "Bayrampaşa",
    "Bağcılar",
    "Başakşehir",
    "Beylikdüzü",
    "Beyoğlu",
    "Beşiktaş",
    "Büyükçekmece",
    "Esenler",
    "Esenyurt",
    "Eyüp",
    "Fatih",
    "Gaziosmanpaşa",
    "Güngören",
    "Kağıthane",
    "Küçükçekmece",
    "Sarıyer",
    "Silivri",
    "Sultangazi",
    "Zeytinburnu",
    "Çatalca",
    "Şişli"
  ],
  "KESİNTİ NEDENİ": [
    "3. Sahis Kaynakli Ariza",
    "3. Sahislarin Müdahalesi",
    "Agaç Temasi",
    "Alpek Arizasi",
    "Araç Çarpmasi",
    "Ariza Kaynakli Sebeke Çalismasi",
    "Asiri Akim Geçici Açma",
    "Asiri Yük",
    "Asiri Yük Arizasi",
    "Bakim Çalismasi",
    "Baslik Arizasi",
    "Buat Arizasi",
    "Direk Arizasi",
    "Diğer",
    "Gecici Ariza",
    "Gerilim Arizasi",
    "Geçici Açma",
    "Iletken Kopugu",
    "Izolatör Arizasi",
    "Kablo Arizasi",
    "Kablo Basligi Arizasi",
    "Kablo Vurugu",
    "Kablo Yanmasi",
    "Kademe Arizasi",
    "Kaide Arizasi",
    "Kesici Arizasi",
    "Klemens / Oksit Arizasi",
    "Kofre Arizasi",
    "Kus Temasi",
    "Manevra Için Kesinti - Ariza",
    "Manevra icin kesinti",
    "Modüler Hücre Arizasi",
    "OG Sigorta Arizasi",
    "OG Sigorta Atmasi",
    "Pano Yanmasi",
    "Parafodur Arizasi",
    "Paralel Açma",
    "SCADA Çalismasi",
    "Sebeke Çalismasi",
    "Sigorta Arizasi",
    "Sigorta Atmasi",
    "Sube Baglantisi",
    "Sube Sökümü",
    "TEIAS Kesintisi",
    "TEIAS Çalismasi",
    "Tedbir Amaçli Kesinti",
    "Toprak Geçici Açma",
    "Trafo Kademe Ayari",
    "Yag Sizintisi",
    "Yatirim Çalismasi"
  ],
  "KESİNTİ SÜRESİ (DK)": {
    "min": 0.0,
    "max": 762.0,
    "median": 212.0,
    "mean": 253.58395721925135
  },
  "Sıcaklık (°C)": {
    "min": 18.5,
    "max": 25.5,
    "median": 22.5,
    "mean": 22.56994652406417
  }
}